{
  "results": [
    {
      "url": "https://www.qualialife.com/shop/qualia-senolytic",
      "title": "Qualia Senolytic: Eliminate Senescent Cells for Healthy Aging",
      "raw_content": "Learn\n\n       About Us\n       Blog\n       Podcast\n       Media\n       FAQ\n\n   Shop\n\n Search \n\n \n    1 shipment (1 x Qualia Senolytic) delivered every 4 weeks \n    Pause or cancel at any time \n\nWhen you choose a subscription for Qualia Senolytic, you'll lock in a $10.00/shipment discount for the life of your subscription — and only pay $39.50 for your first shipment (50% off)!\n\nYour Qualia subscription will renew automatically, but you can cancel or adjust it at any time, with no conditions or mandatory length of subscription. Your payment method will only be charged right before your order ships. For more information, see the Qualia Terms and Conditions.\n\n × \n\n## Qualia Senolytic - Supplement Facts & Ingredients\n\nServing Size: 6 Vegetarian Capsules Servings Per Container: 2 [...] | Amount per Serving | %DV |\n --- |\n| Fisetin (from Rhus succedanea Stem Extract) 1400 mg |  |\n| Quercefit® Quercetin Phytosome (Sophora japonica L. Flower Extract/ Phospholipid Complex from Sunflower) 750 mg |  |\n| Longvida® Optimized Curcumin® Extract (from Curcuma tango Root) 400 mg |  |\n| Olive Leaf Extract 250 mg |  |\n| Soybean Seed Extract 200 mg |  |\n| Luteolin (from Sophora japonica L. Flower Bud Extract) 150 mg |  |\n| Milk Thistle Fruit Extract 125 mg |  |\n| Piperlongumine (from Piper longum Root Extract) 50 mg |  |\n| Senactiv® (Panax notoginseng Root Extract and Rosa roxburghii Fruit Extract) 50 mg |  |\n|  Daily Value (DV) not established |\n\nImage 19Image 20\n\nThe Science Of Feeling Younger TM\n\n## What to Expect [...] ### PIPERLONGUMINE (FROM PIPER LONGUM ROOT EXTRACT)\n\nPiperlongumine is an alkaloid found in many species of pepper plant, and found in abundance in the Asian long pepper plant (_Piper longum_), particularly in its root structure from which we source our piperlongumine. It is the only natural compound known to support a novel mechanism that helps manage senescent cells called oxidation resistance 1 or OXR1.\n\nImage 97\n\n### SENACTIV®\n\nSENACTIV® is a patented blend of notoginseng root and chestnut rose hips. It has been shown to support exercise recovery and management of senescent cells in muscle. This provides an asset within our formula to help counteract the slow workout recoveries that are common with the human aging process.\n\nImage 98\n\n### OLIVE LEAF EXTRACT [...] Image 95\n\n### LONGVIDA OPTIMIZED CURCUMIN® EXTRACT\n\nCurcumin is the pigment in turmeric that results in its yellow-orange coloring. Curcumin appears to have senolytic potential in intervertebral disc cells, but much like quercetin, it has poor bioavailability. LONGVIDA OPTIMIZED CURCUMIN® EXTRACT was developed to overcome this bioavailability hurdle and has been researched in human studies in areas including cognitive function, mood, exercise recovery, and joint health.\n\nImage 96\n\n### PIPERLONGUMINE (FROM PIPER LONGUM ROOT EXTRACT) [...] Image 98\n\n### OLIVE LEAF EXTRACT\n\nOleuropein (a secoiridoid polyphenol) is found in high amounts within olive leaves. Our particular olive leaf extract is standardized for 40% oleuropein. A 2020 study showed that oleuropein supports the management of senescent chondrocytes—chondrocytes are the cells that create cartilage and support healthy joints (an area of our bodies which commonly experience noticeable negative aging symptoms).\n\nImage 99\n\n### MILK THISTLE FRUIT EXTRACT",
      "images": []
    }
  ],
  "failed_results": [],
  "response_time": 0.22,
  "request_id": "55ee9e8a-08f7-46df-a7b2-6d762b8bf2b9"
}
